sqlite_icu.py
icu.cpython-37m-i386-linux-gnu.so
sqlite_icu-1.0.dist-info/WHEEL
sqlite_icu-1.0.dist-info/METADATA
sqlite_icu-1.0.dist-info/RECORD
sqlite_icu-1.0.dist-info/top_level.txt
sqlite_icu-1.0.dist-info/LICENSE
sqlite_icu.libs/libicui18n-21c63583.so.50.2
sqlite_icu.libs/libicudata-386647f2.so.50.2
sqlite_icu.libs/libicuuc-d174bdbd.so.50.2
