Metadata-Version: 2.1
Name: sqlite-icu
Version: 1.0
Summary: Loadable ICU extension for sqlite
Home-page: http://github.com/karlb/sqlite-icu
License: UNKNOWN
Platform: UNKNOWN
License-File: LICENSE
